cr8/__init__.py
cr8/__main__.py
cr8/aio.py
cr8/bench_spec.py
cr8/cli.py
cr8/clients.py
cr8/engine.py
cr8/exceptions.py
cr8/fake_providers.py
cr8/insert_fake_data.py
cr8/insert_from_sql.py
cr8/insert_json.py
cr8/java_magic.py
cr8/log.py
cr8/metrics.py
cr8/misc.py
cr8/py.typed
cr8/reindex.py
cr8/run_crate.py
cr8/run_spec.py
cr8/run_track.py
cr8/timeit.py
cr8-0.29.1.dist-info/licenses/LICENSE
cr8-0.29.1.dist-info/METADATA
cr8-0.29.1.dist-info/WHEEL
cr8-0.29.1.dist-info/entry_points.txt
cr8-0.29.1.dist-info/top_level.txt
cr8-0.29.1.dist-info/RECORD
