Metadata-Version: 2.4
Name: cr8
Version: 0.29.1
Summary: A collection of command line tools for crate devs
Home-page: https://codeberg.org/mfussenegger/cr8
Author: Mathias Fußenegger
Author-email: pip@zignar.net
License: MIT
Classifier: Development Status :: 4 - Beta
Classifier: Programming Language :: Python :: 3
Classifier: Programming Language :: Python :: 3.11
Classifier: Programming Language :: Python :: 3.12
Classifier: Programming Language :: Python :: 3.13
Classifier: Programming Language :: Python :: 3.14
Requires-Python: >=3.11
License-File: LICENSE
Requires-Dist: argh
Requires-Dist: tqdm
Requires-Dist: Faker<5.0,>=4.0
Requires-Dist: aiohttp<4,>=3.3
Requires-Dist: asyncpg
Provides-Extra: extra
Requires-Dist: uvloop>=0.18; extra == "extra"
Requires-Dist: pysimdjson; extra == "extra"
Provides-Extra: dev
Requires-Dist: asyncpg-stubs; extra == "dev"
Requires-Dist: mypy; extra == "dev"
Dynamic: author
Dynamic: author-email
Dynamic: classifier
Dynamic: description
Dynamic: description-content-type
Dynamic: home-page
Dynamic: license
Dynamic: license-file
Dynamic: provides-extra
Dynamic: requires-dist
Dynamic: requires-python
Dynamic: summary
